cepy_tools/__init__.py
cepy_tools/cepy.py
cepy_tools/pinyin.py
cepy_tools/serialize.py
cepy_tools/word_segmentation.py
cepy_tools-0.1.0.dist-info/METADATA
cepy_tools-0.1.0.dist-info/WHEEL
cepy_tools-0.1.0.dist-info/licenses/COPYING
cepy_tools-0.1.0.dist-info/RECORD
