Metadata-Version: 2.4
Name: cepy-tools
Version: 0.1.0
Summary: A sleepy little collection of chinese<->english tools
Author-email: Erik Swanson <theerikswanson@gmail.com>
License-Expression: GPL-3.0-or-later
License-File: COPYING
Requires-Python: >=3.10
Requires-Dist: cepy-dict>=2025.2.20
